{
  "nodeType": "n8n-nodes-base.apiTemplateIo",
  "displayName": "APITemplate.io",
  "description": "Consume the APITemplate.io API",
  "version": 1,
  "properties": [
    {
      "name": "resource",
      "displayName": "Resource",
      "type": "options",
      "default": "image",
      "options": [
        {
          "name": "Account",
          "value": "account"
        },
        {
          "name": "Image",
          "value": "image"
        },
        {
          "name": "PDF",
          "value": "pdf"
        }
      ]
    },
    {
      "name": "operation",
      "displayName": "Operation",
      "type": "options",
      "default": "create",
      "required": true,
      "options": [
        {
          "name": "Create",
          "value": "create"
        }
      ],
      "displayOptions": {
        "show": {
          "resource": [
            "image"
          ]
        }
      }
    },
    {
      "name": "imageTemplateId",
      "displayName": "Template Name or ID",
      "type": "options",
      "default": "",
      "description": "ID of the image template to use. Choose from the list, or specify an ID using an <a href=\"https://docs.n8n.io/code/expressions/\">expression</a>.",
      "required": true,
      "displayOptions": {
        "show": {
          "resource": [
            "image"
          ],
          "operation": [
            "create"
          ]
        }
      }
    },
    {
      "name": "pdfTemplateId",
      "displayName": "Template Name or ID",
      "type": "options",
      "default": "",
      "description": "ID of the PDF template to use. Choose from the list, or specify an ID using an <a href=\"https://docs.n8n.io/code/expressions/\">expression</a>.",
      "required": true,
      "displayOptions": {
        "show": {
          "resource": [
            "pdf"
          ],
          "operation": [
            "create"
          ]
        }
      }
    },
    {
      "name": "jsonParameters",
      "displayName": "JSON Parameters",
      "type": "boolean",
      "default": false,
      "displayOptions": {
        "show": {
          "resource": [
            "pdf",
            "image"
          ],
          "operation": [
            "create"
          ]
        }
      }
    },
    {
      "name": "download",
      "displayName": "Download",
      "type": "boolean",
      "default": false,
      "description": "Name of the binary property to which to write the data of the read file",
      "displayOptions": {
        "show": {
          "resource": [
            "pdf",
            "image"
          ],
          "operation": [
            "create"
          ]
        }
      }
    },
    {
      "name": "binaryProperty",
      "displayName": "Put Output File in Field",
      "type": "string",
      "default": "data",
      "required": true,
      "displayOptions": {
        "show": {
          "resource": [
            "pdf",
            "image"
          ],
          "operation": [
            "create"
          ],
          "download": [
            true
          ]
        }
      }
    },
    {
      "name": "overridesJson",
      "displayName": "Overrides (JSON)",
      "type": "json",
      "default": "",
      "placeholder": "[ {\"name\": \"text_1\", \"text\": \"hello world\", \"textBackgroundColor\": \"rgba(246, 243, 243, 0)\" } ]",
      "displayOptions": {
        "show": {
          "resource": [
            "image"
          ],
          "operation": [
            "create"
          ],
          "jsonParameters": [
            true
          ]
        }
      }
    },
    {
      "name": "propertiesJson",
      "displayName": "Properties (JSON)",
      "type": "json",
      "default": "",
      "placeholder": "{ \"name\": \"text_1\" }",
      "displayOptions": {
        "show": {
          "resource": [
            "pdf"
          ],
          "operation": [
            "create"
          ],
          "jsonParameters": [
            true
          ]
        }
      }
    },
    {
      "name": "overridesUi",
      "displayName": "Overrides",
      "type": "fixedCollection",
      "default": {},
      "description": "Name of the property",
      "placeholder": "Add Override",
      "typeOptions": {
        "multipleValues": true
      },
      "displayOptions": {
        "show": {
          "resource": [
            "image"
          ],
          "operation": [
            "create"
          ],
          "jsonParameters": [
            false
          ]
        }
      }
    },
    {
      "name": "propertiesUi",
      "displayName": "Properties",
      "type": "fixedCollection",
      "default": {},
      "description": "Name of the property",
      "placeholder": "Add Property",
      "typeOptions": {
        "multipleValues": true
      },
      "displayOptions": {
        "show": {
          "resource": [
            "pdf"
          ],
          "operation": [
            "create"
          ],
          "jsonParameters": [
            false
          ]
        }
      }
    },
    {
      "name": "options",
      "displayName": "Options",
      "type": "collection",
      "default": {},
      "description": "The name of the downloaded image/pdf. It has to include the extension. For example: report.pdf",
      "placeholder": "Add Field",
      "options": [
        {
          "name": "fileName",
          "displayName": "File Name",
          "type": "string",
          "default": "",
          "description": "The name of the downloaded image/pdf. It has to include the extension. For example: report.pdf"
        }
      ],
      "displayOptions": {
        "show": {
          "operation": [
            "create"
          ],
          "resource": [
            "pdf",
            "image"
          ],
          "download": [
            true
          ]
        }
      }
    }
  ],
  "credentialsConfig": [
    {
      "name": "apiTemplateIoApi",
      "required": true
    },
    {
      "name": "resource",
      "required": false
    },
    {
      "name": "operation",
      "required": true
    },
    {
      "name": "operation",
      "required": true
    },
    {
      "name": "operation",
      "required": true
    },
    {
      "name": "imageTemplateId",
      "required": true
    },
    {
      "name": "propertiesJson",
      "required": false
    },
    {
      "name": "propertiesUi",
      "required": false
    },
    {
      "name": "options",
      "required": false
    }
  ],
  "io": {
    "inputs": [],
    "outputs": [],
    "outputNames": [],
    "hints": {}
  },
  "wiring": {
    "role": "generic",
    "requires": [],
    "optional": [],
    "consumedBy": [],
    "consumes": [],
    "produces": []
  }
}